CHANGES.txt
LICENSE.txt
MANIFEST.in
README.rst
setup.py
django_richtext_blog.egg-info/PKG-INFO
django_richtext_blog.egg-info/SOURCES.txt
django_richtext_blog.egg-info/dependency_links.txt
django_richtext_blog.egg-info/not-zip-safe
django_richtext_blog.egg-info/requires.txt
django_richtext_blog.egg-info/top_level.txt
richtext_blog/__init__.py
richtext_blog/__init__.pyc
richtext_blog/admin.py
richtext_blog/admin.pyc
richtext_blog/context_processors.py
richtext_blog/context_processors.pyc
richtext_blog/custom_dashboard.py
richtext_blog/custom_dashboard.pyc
richtext_blog/forms.py
richtext_blog/forms.pyc
richtext_blog/models.py
richtext_blog/models.pyc
richtext_blog/urls.py
richtext_blog/urls.pyc
richtext_blog/views.py
richtext_blog/views.pyc
richtext_blog/static/blog-style.css
richtext_blog/static/jquery-1.7.2.min.js
richtext_blog/static/pygments.css
richtext_blog/static/rss_24x24.png
richtext_blog/templates/base.html
richtext_blog/templates/richtext_blog/blog-macros.html
richtext_blog/templates/richtext_blog/post-detail.html
richtext_blog/templates/richtext_blog/post-list.html
richtext_blog/templates/richtext_blog/tag-view.html
richtext_blog/templatetags/__init__.py
richtext_blog/templatetags/__init__.pyc
richtext_blog/templatetags/blog_extras.py
richtext_blog/templatetags/blog_extras.pyc
richtext_blog/templatetags/macros.py
richtext_blog/templatetags/macros.pyc