Metadata-Version: 1.0
Name: django-richtext-blog
Version: 0.8.6
Summary: A django app that implements a blog with the features we've grown accustomed to. Features: Rich text editing with TinyMCE; Full image upload support; Tags; Comments; Spam prevention; Atom/RSS feeds; Example templates; Code syntax highlighting; SEO optimised urls and more.
Home-page: https://github.com/timmygee/django-richtext-blog
Author: Tim Godfrey
Author-email: http://www.wholebaked.com.au/contact
License: BSD licence, see LICENCE.txt
Keywords: django blog richtext tinymce
Platform: UNKNOWN
Classifier: Development Status :: 4 - Beta
Classifier: Environment :: Console
Classifier: Environment :: Web Environment
Classifier: Framework :: Django
Classifier: Intended Audience :: Developers
Classifier: Intended Audience :: End Users/Desktop
Classifier: License :: OSI Approved :: BSD License
Classifier: Natural Language :: English
Classifier: Operating System :: OS Independent
Classifier: Programming Language :: Python
Classifier: Topic :: Internet :: WWW/HTTP
Classifier: Topic :: Internet :: WWW/HTTP :: Dynamic Content :: News/Diary
